chalicelib_smaht/__init__.py
chalicelib_smaht/app_utils.py
chalicelib_smaht/buckets.py
chalicelib_smaht/check_schedules.py
chalicelib_smaht/check_setup.json
chalicelib_smaht/check_setup.json-local
chalicelib_smaht/check_setup.json-smaht-wolf
chalicelib_smaht/checks/__init__.py
chalicelib_smaht/checks/audit_checks.py
chalicelib_smaht/checks/ecs_checks.py
chalicelib_smaht/checks/es_checks.py
chalicelib_smaht/checks/helpers/confchecks.py
chalicelib_smaht/checks/helpers/constants.py
chalicelib_smaht/checks/helpers/lifecycle_utils.py
chalicelib_smaht/checks/helpers/linecount_dicts.py
chalicelib_smaht/checks/helpers/utils.py
chalicelib_smaht/checks/helpers/wfr_utils.py
chalicelib_smaht/checks/helpers/wfrset_utils.py
chalicelib_smaht/checks/helpers/wrangler_utils.py
chalicelib_smaht/checks/lifecycle_checks.py
chalicelib_smaht/checks/system_checks.py
chalicelib_smaht/checks/wfr_checks.py
chalicelib_smaht/checks/wrangler_checks.py
chalicelib_smaht/deploy.py
chalicelib_smaht/gitinfo.json
chalicelib_smaht/package.py
chalicelib_smaht/scripts/local_check_execution.py
chalicelib_smaht/vars.py
foursight_smaht-0.8.16.dist-info/LICENSE.txt
foursight_smaht-0.8.16.dist-info/METADATA
foursight_smaht-0.8.16.dist-info/WHEEL
foursight_smaht-0.8.16.dist-info/entry_points.txt
foursight_smaht-0.8.16.dist-info/RECORD
