Metadata-Version: 2.1
Name: foursight-smaht
Version: 0.8.16
Summary: Serverless Chalice Application for Monitoring
License: MIT
Author: 4DN-DCIC Team
Author-email: support@4dnucleome.org
Requires-Python: >=3.9,<3.13
Classifier: License :: OSI Approved :: MIT License
Classifier: Programming Language :: Python :: 3
Classifier: Programming Language :: Python :: 3.9
Classifier: Programming Language :: Python :: 3.10
Classifier: Programming Language :: Python :: 3.11
Requires-Dist: Jinja2 (>=3.1.2,<4.0.0)
Requires-Dist: MarkupSafe (>=2.1.3,<3.0.0)
Requires-Dist: PyJWT (>=2.5.0,<3.0.0)
Requires-Dist: awscli (>=1.33.18,<2.0.0)
Requires-Dist: click (>=7.1.2,<8.0.0)
Requires-Dist: cron-descriptor (>=1.4.0,<2.0.0)
Requires-Dist: dcicutils (>=8.16.6,<9.0.0)
Requires-Dist: elasticsearch (==7.13.4)
Requires-Dist: elasticsearch-dsl (>=7.0.0,<8.0.0)
Requires-Dist: foursight-core (>=5.7.0,<6.0.0)
Requires-Dist: geocoder (==1.38.1)
Requires-Dist: gitpython (>=3.1.2,<4.0.0)
Requires-Dist: google-api-python-client (>=1.12.5,<2.0.0)
Requires-Dist: magma-suite (>=3.6.0,<4.0.0)
Requires-Dist: packaging (>=23.0,<24.0)
Requires-Dist: pytest (>=7.4.2,<8.0.0)
Requires-Dist: pytest-redis (>=3.0.2,<4.0.0)
Requires-Dist: pytz (>=2020.1,<2021.0)
Requires-Dist: tibanna-ff (>=3.5.0,<4.0.0)
Requires-Dist: tzlocal (>=5.1,<6.0)
